{"cameraMode":{"drawMode":0,"name":"Shaded","section":"Shading Mode"},"sceneLighting":true,"audioPlay":false,"sceneViewState":{"m_AlwaysRefresh":false,"showFog":true,"showSkybox":true,"showFlares":true,"showImageEffects":true,"showParticleSystems":true,"showVisualEffectGraphs":true,"m_FxEnabled":true},"in2DMode":false,"pivot":{"x":-2.2797794342041017,"y":4.396800994873047,"z":-3.4550561904907228},"rotation":{"x":0.2178836166858673,"y":0.04682458937168121,"z":-0.01046864502131939,"w":0.9748095273971558},"size":6.651075839996338,"orthographic":false}